{
  "name": "Daily Prep → BowlMama WhatsApp (06:30 KL)",
  "active": false,
  "nodes": [
    {
      "parameters": {
        "rule": {
          "interval": [
            {
              "field": "cronExpression",
              "expression": "30 6 * * *"
            }
          ]
        }
      },
      "id": "trigger-630-kl",
      "name": "Cron 06:30 KL",
      "type": "n8n-nodes-base.scheduleTrigger",
      "typeVersion": 1.2,
      "position": [200, 400],
      "notes": "Daily at 06:30 Asia/Kuala_Lumpur. Set timezone in n8n global settings (Settings → General → Timezone) OR on this node's 'Trigger Timezone' if available, else cron runs in UTC."
    },
    {
      "parameters": {
        "method": "GET",
        "url": "https://www.incredibowl.my/api/n8n/daily-prep",
        "authentication": "genericCredentialType",
        "genericAuthType": "httpHeaderAuth",
        "sendHeaders": false,
        "sendQuery": false,
        "options": {
          "timeout": 30000,
          "response": {
            "response": {
              "responseFormat": "json"
            }
          }
        }
      },
      "id": "http-fetch-prep",
      "name": "Fetch Daily Prep",
      "type": "n8n-nodes-base.httpRequest",
      "typeVersion": 4.2,
      "position": [440, 400],
      "credentials": {
        "httpHeaderAuth": {
          "id": "REPLACE_WITH_CREDENTIAL_ID",
          "name": "Incredibowl N8N API Key"
        }
      },
      "notes": "Uses Header Auth credential. Create it in n8n: Credentials → New → Header Auth → Name='Authorization', Value='Bearer <YOUR_N8N_API_KEY>'. IMPORTANT: hit www.incredibowl.my (not incredibowl.my) — apex 307-redirects and curl/n8n drops Authorization across the hop."
    },
    {
      "parameters": {
        "jsCode": "// Build the complete Meta Cloud API payload here as a JS object so\n// the HTTP node only needs JSON.stringify($json.payload). Avoids the\n// newline-in-JSON parse error that happens when summaryText (which\n// contains real \\n chars from the prep list) is naively substituted\n// into a JSON string template via n8n expression.\n//\n// WhatsApp template parameters reject newlines, tabs, and 5+\n// consecutive spaces (error #132018). The endpoint's summaryText is\n// now already a single line with format\n//   \"<main dishes> ｜加料：<add-ons>\"\n// so we can pass it straight through; safe() still scrubs as a defence.\n\nconst data = $input.first().json;\n\nconst safe = (s) => {\n  if (s === undefined || s === null) return '无';\n  const str = String(s)\n    .replace(/\\n/g, ' / ')\n    .replace(/\\t/g, ' ')\n    .replace(/\\s{5,}/g, '    ')\n    .trim();\n  return str.length > 0 ? str : '无';\n};\n\n// Test recipient: your own phone. Change to BowlMama's number after\n// the first manual Execute Workflow round-trip confirms the template\n// renders correctly.\nconst RECIPIENT = '60165119118';\n\nconst payload = {\n  messaging_product: 'whatsapp',\n  to: RECIPIENT,\n  type: 'template',\n  template: {\n    name: 'daily_prep_summary',\n    language: { code: 'zh_CN' },\n    components: [\n      {\n        type: 'body',\n        parameters: [\n          { type: 'text', text: safe(data.date) },\n          { type: 'text', text: safe(data.lunch?.count ?? 0) },\n          { type: 'text', text: safe(data.lunch?.summaryText) },\n          { type: 'text', text: safe(data.dinner?.count ?? 0) },\n          { type: 'text', text: safe(data.dinner?.summaryText) },\n          { type: 'text', text: safe(data.notesText) },\n        ],\n      },\n    ],\n  },\n};\n\nreturn [{ json: { payload, _raw: data } }];\n"
      },
      "id": "code-format-vars",
      "name": "Build Meta Payload",
      "type": "n8n-nodes-base.code",
      "typeVersion": 2,
      "position": [680, 400],
      "notes": "Builds the complete Meta Cloud API payload as a JS object. Change RECIPIENT here to switch between test (your phone) and prod (BowlMama)."
    },
    {
      "parameters": {
        "method": "POST",
        "url": "https://graph.facebook.com/v18.0/REPLACE_WITH_YOUR_PHONE_NUMBER_ID/messages",
        "authentication": "genericCredentialType",
        "genericAuthType": "httpHeaderAuth",
        "sendBody": true,
        "specifyBody": "json",
        "jsonBody": "={{ JSON.stringify($json.payload) }}",
        "options": {
          "timeout": 30000
        }
      },
      "id": "wa-send-template",
      "name": "Send WhatsApp Template",
      "type": "n8n-nodes-base.httpRequest",
      "typeVersion": 4.2,
      "position": [920, 400],
      "credentials": {
        "httpHeaderAuth": {
          "id": "REPLACE_WITH_WA_TOKEN_CREDENTIAL_ID",
          "name": "Incredibowl WhatsApp Token"
        }
      },
      "notes": "Raw HTTP POST to Meta Cloud API. Built-in n8n WhatsApp node doesn't support template messages in v2.14, so we hit the API directly. The body is JSON.stringify of the JS object built in the previous node — avoids n8n expression substitution mangling newlines inside JSON string literals."
    },
    {
      "parameters": {
        "jsCode": "// Surface failures clearly. Replace this with a Slack/Email node\n// hooked to your own number if you want push notifications on failure.\nconst err = $input.first().json;\nconsole.error('[daily-prep] WhatsApp send failed', JSON.stringify(err));\nreturn [{ json: { error: err } }];\n"
      },
      "id": "code-error-log",
      "name": "Log Error",
      "type": "n8n-nodes-base.code",
      "typeVersion": 2,
      "position": [920, 600],
      "notes": "Catch-all error logger. Swap for Slack/Email/Telegram node to actually be notified when 06:30 push fails. Right now this only writes to n8n execution logs."
    }
  ],
  "connections": {
    "Cron 06:30 KL": {
      "main": [
        [
          { "node": "Fetch Daily Prep", "type": "main", "index": 0 }
        ]
      ]
    },
    "Fetch Daily Prep": {
      "main": [
        [
          { "node": "Build Meta Payload", "type": "main", "index": 0 }
        ]
      ]
    },
    "Build Meta Payload": {
      "main": [
        [
          { "node": "Send WhatsApp Template", "type": "main", "index": 0 }
        ]
      ]
    },
    "Send WhatsApp Template": {
      "main": [
        []
      ]
    }
  },
  "settings": {
    "executionOrder": "v1",
    "saveExecutionProgress": true,
    "saveManualExecutions": true,
    "saveDataErrorExecution": "all",
    "saveDataSuccessExecution": "all",
    "errorWorkflow": "",
    "timezone": "Asia/Kuala_Lumpur"
  },
  "tags": [
    { "name": "incredibowl" },
    { "name": "production" }
  ],
  "meta": {
    "templateCredsSetupCompleted": false,
    "instanceId": ""
  },
  "pinData": {}
}
